walt/__init__.py
walt/client/__init__.py
walt/client/g5k/__init__.py
walt/client/g5k/autocomplete.py
walt/client/g5k/cli.py
walt/client/g5k/myexeco.py
walt/client/g5k/plugin.py
walt/client/g5k/printer.py
walt/client/g5k/reboot.py
walt/client/g5k/release.py
walt/client/g5k/reservation.py
walt/client/g5k/startup.py
walt/client/g5k/tools.py
walt/client/g5k/types.py
walt/client/g5k/wait.py
walt/client/g5k/deploy/__init__.py
walt/client/g5k/deploy/deploy.py
walt/client/g5k/deploy/helper.py
walt/client/g5k/deploy/remote-server-conf.py
walt/client/g5k/deploy/status.py
walt/client/g5k/recipes/__init__.py
walt/client/g5k/recipes/const.py
walt/client/g5k/recipes/editor.py
walt/client/g5k/recipes/manager.py
walt/client/g5k/recipes/printer.py
walt/client/g5k/recipes/tools.py
walt/client/metadata/__init__.py
walt/client/metadata/g5k.py
walt_client_g5k-10.0.dist-info/METADATA
walt_client_g5k-10.0.dist-info/WHEEL
walt_client_g5k-10.0.dist-info/entry_points.txt
walt_client_g5k-10.0.dist-info/top_level.txt
walt_client_g5k-10.0.dist-info/RECORD
